[
  {
    "fields": [
      {
        "description": "The name of your site, usually your company/brand name.",
        "name": "title",
        "type": "string",
        "title": "Site Title"
      },
      {
        "description": "Describe your site for search engines and social media.",
        "name": "description",
        "type": "text",
        "title": "Site Description"
      },
      {
        "description": "Add keywords that describe your site.",
        "of": [
          {
            "type": "string"
          }
        ],
        "name": "keywords",
        "type": "array"
      },
      {
        "name": "author",
        "type": "string",
        "title": "Site Author"
      },
      {
        "options": {
          "hotspot": true
        },
        "fields": [
          {
            "description": "Important for SEO and accessibility.",
            "name": "alt",
            "type": "string",
            "title": "Alt text"
          }
        ],
        "name": "logo",
        "type": "image",
        "title": "Site Logo"
      },
      {
        "options": {
          "hotspot": true
        },
        "description": "A version of the logo for use on dark backgrounds.",
        "fields": [
          {
            "description": "Important for SEO and accessibility.",
            "name": "alt",
            "type": "string",
            "title": "Alt text"
          }
        ],
        "name": "logoWhite",
        "type": "image",
        "title": "White/Inverted Logo"
      },
      {
        "description": "Recommended: .ico or .png, square dimensions (e.g., 32x32, 64x64).",
        "name": "favicon",
        "type": "image"
      },
      {
        "description": "Primary contact email address for the site.",
        "name": "contactEmail",
        "type": "string"
      },
      {
        "description": "Primary contact phone number for the site.",
        "name": "contactPhone",
        "type": "string"
      },
      {
        "options": {
          "hotspot": true
        },
        "description": "Used for social media cards when no image is added.",
        "name": "defaultOgImage",
        "type": "image",
        "title": "Default OG Image"
      },
      {
        "validation": [
          {
            "rules": [
              {
                "flag": "uri",
                "constraint": {
                  "options": {
                    "scheme": [
                      "/^http$/",
                      "/^https$/"
                    ],
                    "allowRelative": false,
                    "relativeOnly": false,
                    "allowCredentials": false
                  }
                }
              }
            ],
            "level": "error"
          }
        ],
        "description": "The main site URL. Used to create canonical and alternate language links.",
        "name": "url",
        "type": "url",
        "title": "Site URL"
      },
      {
        "of": [
          {
            "fields": [
              {
                "name": "title",
                "type": "string"
              },
              {
                "options": {
                  "source": "title",
                  "maxLength": 96
                },
                "validation": [
                  {
                    "rules": [
                      {
                        "flag": "custom"
                      }
                    ],
                    "level": "error"
                  }
                ],
                "name": "navItemUrl",
                "type": "slug",
                "title": "Navigation Item URL"
              }
            ],
            "type": "object"
          }
        ],
        "name": "mainNav",
        "type": "array",
        "title": "Main Navigation"
      },
      {
        "fields": [
          {
            "name": "copyrightName",
            "type": "string",
            "title": "Copyright name"
          },
          {
            "description": "Text displayed in the footer (e.g., © YEAR Vibe Supply. All rights reserved.)",
            "name": "footerText",
            "type": "string"
          },
          {
            "of": [
              {
                "fields": [
                  {
                    "name": "title",
                    "type": "string"
                  },
                  {
                    "options": {
                      "source": "title",
                      "maxLength": 96
                    },
                    "validation": [
                      {
                        "rules": [
                          {
                            "flag": "custom"
                          }
                        ],
                        "level": "error"
                      }
                    ],
                    "name": "navItemUrl",
                    "type": "slug",
                    "title": "Navigation Item URL"
                  }
                ],
                "type": "object"
              }
            ],
            "name": "footerNav",
            "type": "array",
            "title": "Footer Navigation"
          }
        ],
        "name": "footer",
        "type": "object"
      },
      {
        "of": [
          {
            "fields": [
              {
                "name": "title",
                "type": "string"
              },
              {
                "validation": [
                  {
                    "rules": [
                      {
                        "flag": "uri",
                        "constraint": {
                          "options": {
                            "scheme": [
                              "/^http$/",
                              "/^https$/"
                            ],
                            "allowRelative": false,
                            "relativeOnly": false,
                            "allowCredentials": false
                          }
                        }
                      }
                    ],
                    "level": "error"
                  }
                ],
                "name": "url",
                "type": "url",
                "title": "URL"
              }
            ],
            "type": "object"
          }
        ],
        "name": "socialLinks",
        "type": "array"
      }
    ],
    "name": "siteSettings",
    "type": "document"
  },
  {
    "fields": [
      {
        "initialValue": "Homepage",
        "hidden": true,
        "name": "title",
        "type": "string"
      },
      {
        "fields": [
          {
            "of": [
              {
                "options": {
                  "hotspot": true
                },
                "fields": [
                  {
                    "description": "Describe this image for accessibility and SEO.",
                    "name": "alt",
                    "type": "string",
                    "title": "Image Alt Text / Name"
                  }
                ],
                "type": "image"
              }
            ],
            "name": "images",
            "type": "array",
            "title": "Hero Images"
          }
        ],
        "name": "mainHero",
        "type": "object",
        "title": "Main Hero Section"
      },
      {
        "fields": [
          {
            "options": {
              "hotspot": true
            },
            "description": "Logo image displayed in the About Vibe Supply card",
            "name": "logo",
            "type": "image",
            "title": "Section Logo"
          },
          {
            "description": "Intro text displayed above the package features list.",
            "name": "featuresIntro",
            "type": "string",
            "title": "Features Intro Text"
          },
          {
            "description": "Bullet points describing what is included in the package.",
            "of": [
              {
                "fields": [
                  {
                    "name": "text",
                    "type": "string",
                    "title": "Feature Text"
                  }
                ],
                "type": "object"
              }
            ],
            "name": "features",
            "type": "array",
            "title": "Package Features"
          },
          {
            "description": "Text shown at the bottom of the About Vibe Supply card (e.g., Elevating events since 2015)",
            "name": "footer",
            "type": "string",
            "title": "Section Footer Text"
          },
          {
            "options": {
              "hotspot": true
            },
            "fields": [
              {
                "description": "Describe this image for accessibility and SEO.",
                "name": "imageAlt",
                "type": "string",
                "title": "Image Alt Text / SEO Title"
              },
              {
                "description": "Title displayed on the image card (e.g., Unforgettable Experiences)",
                "name": "imageTitle",
                "type": "string",
                "title": "Image Card Title"
              },
              {
                "description": "Subtitle displayed on the image card (e.g., Let's create magical moments for your special event)",
                "name": "imageSubtitle",
                "type": "string",
                "title": "Image Card Subtitle"
              }
            ],
            "name": "image",
            "type": "image",
            "title": "Section Image"
          }
        ],
        "name": "aboutVibeSupply",
        "type": "object",
        "title": "About Vibe Supply Section"
      }
    ],
    "name": "homepage",
    "type": "document"
  }
]